xion/__init__.py
xion/__main__.py
xion/xfconf.py
xion/xion.py
xion-0.0.2.dist-info/LICENSE.txt
xion-0.0.2.dist-info/METADATA
xion-0.0.2.dist-info/WHEEL
xion-0.0.2.dist-info/entry_points.txt
xion-0.0.2.dist-info/top_level.txt
xion-0.0.2.dist-info/RECORD
