Metadata-Version: 2.1
Name: xion
Version: 0.0.2
Summary: JSON interface to Xfconf
Home-page: https://github.com/Dece/Xion
Author: dece
Author-email: shgck@pistache.land
License: MIT
Platform: UNKNOWN
Classifier: Environment :: Console
Classifier: License :: OSI Approved :: MIT License
Classifier: Programming Language :: Python :: 3
Classifier: Programming Language :: Python :: 3.7
Requires-Python: >= 3.7
